PyTokenCounter/__init__.py
PyTokenCounter/cli.py
PyTokenCounter/core.py
PyTokenCounter/encoding_utils.py
PyTokenCounter/file_tokens.py
PyTokenCounter/progress.py
pytokencounter-1.9.0.dist-info/licenses/LICENSE
tests/test_models.py
tests/test_tokenization.py
tests/test_utils.py
pytokencounter-1.9.0.dist-info/METADATA
pytokencounter-1.9.0.dist-info/WHEEL
pytokencounter-1.9.0.dist-info/entry_points.txt
pytokencounter-1.9.0.dist-info/top_level.txt
pytokencounter-1.9.0.dist-info/RECORD
