Metadata-Version: 2.4
Name: PyTokenCounter
Version: 1.9.0
Summary: A Python library for tokenizing text and counting tokens using various encoding schemes.
Author-email: Kaden Gruizenga <kgruiz@umich.edu>
License:                     GNU GENERAL PUBLIC LICENSE
Project-URL: homepage, https://github.com/kgruiz/PyTokenCounter
Project-URL: repository, https://github.com/kgruiz/PyTokenCounter
Project-URL: documentation, https://github.com/kgruiz/PyTokenCounter#readme
Project-URL: bug_tracker, https://github.com/kgruiz/PyTokenCounter/issues
Keywords: tokenization,encoding,tiktoken,openai,gpt,language-model,llm,transformers,natural-language-processing,nlp,machine-learning,ai,text-processing,language-models
Classifier: Development Status :: 5 - Production/Stable
Classifier: Intended Audience :: Developers
Classifier: Intended Audience :: Science/Research
Classifier: Topic :: Software Development :: Libraries :: Python Modules
Classifier: Topic :: Scientific/Engineering :: Artificial Intelligence
Classifier: Topic :: Text Processing :: Linguistic
Classifier: License :: OSI Approved :: MIT License
Classifier: Programming Language :: Python :: 3
Classifier: Programming Language :: Python :: 3.11
Classifier: Programming Language :: Python :: 3.12
Classifier: Programming Language :: Python :: 3 :: Only
Classifier: Operating System :: OS Independent
Requires-Python: >=3.11
License-File: LICENSE
Requires-Dist: tiktoken>=0.8.0
Requires-Dist: rich>=13.9.4
Requires-Dist: chardet>=5.2.0
Requires-Dist: colorlog>=6.9.0
Requires-Dist: pytest>=7.4.0
Requires-Dist: flake8>=6.1.0
Provides-Extra: test
Requires-Dist: pytest>=7.4.0; extra == "test"
Requires-Dist: flake8>=6.1.0; extra == "test"
Dynamic: license-file
